resource_lister/__init__.py
resource_lister/main.py
resource_lister/api/rl_api.py
resource_lister/boto_formatter/__init__.py
resource_lister/boto_formatter/core_formatter.py
resource_lister/boto_formatter/service_formatter.py
resource_lister/boto_formatter/json_util/__init__.py
resource_lister/boto_formatter/json_util/json_util.py
resource_lister/boto_formatter/service_config_mgr/__init__.py
resource_lister/boto_formatter/service_config_mgr/service_config.py
resource_lister/boto_formatter/service_config_mgr/service_configs/accessanalyzer.json
resource_lister/boto_formatter/service_config_mgr/service_configs/account.json
resource_lister/boto_formatter/service_config_mgr/service_configs/acm.json
resource_lister/boto_formatter/service_config_mgr/service_configs/amp.json
resource_lister/boto_formatter/service_config_mgr/service_configs/apigateway.json
resource_lister/boto_formatter/service_config_mgr/service_configs/appconfig.json
resource_lister/boto_formatter/service_config_mgr/service_configs/appflow.json
resource_lister/boto_formatter/service_config_mgr/service_configs/budgets.json
resource_lister/boto_formatter/service_config_mgr/service_configs/cleanrooms.json
resource_lister/boto_formatter/service_config_mgr/service_configs/cloudformation.json
resource_lister/boto_formatter/service_config_mgr/service_configs/cloudfront.json
resource_lister/boto_formatter/service_config_mgr/service_configs/cloudtrail.json
resource_lister/boto_formatter/service_config_mgr/service_configs/cloudwatch.json
resource_lister/boto_formatter/service_config_mgr/service_configs/codecommit.json
resource_lister/boto_formatter/service_config_mgr/service_configs/dynamodb.json
resource_lister/boto_formatter/service_config_mgr/service_configs/ec2.json
resource_lister/boto_formatter/service_config_mgr/service_configs/ecs.json
resource_lister/boto_formatter/service_config_mgr/service_configs/efs.json
resource_lister/boto_formatter/service_config_mgr/service_configs/eks.json
resource_lister-2.2.0.dist-info/LICENSE
resource_lister-2.2.0.dist-info/METADATA
resource_lister-2.2.0.dist-info/NOTICE
resource_lister-2.2.0.dist-info/WHEEL
resource_lister-2.2.0.dist-info/entry_points.txt
resource_lister-2.2.0.dist-info/top_level.txt
resource_lister-2.2.0.dist-info/RECORD
