Metadata-Version: 2.1
Name: resource-lister
Version: 2.2.0
Summary: Resource Lister
Author-email: Abhijit Rajeshirke <rajeabh@amazon.com>
Project-URL: Homepage, https://github.com/awslabs/resource-lister
Project-URL: Bug Tracker, https://github.com/awslabs/resource-lister/issues
Classifier: Programming Language :: Python :: 3
Classifier: License :: OSI Approved :: Apache Software License
Classifier: Operating System :: OS Independent
Requires-Python: >=3.7
License-File: LICENSE
License-File: NOTICE
Requires-Dist: boto3>=1.15.0
